{
  "model": "slowfast_r101",
  "frames_dir": "/home/jovyan/kau-muhayu-multimodal-harmful-content-detect/임영재/팀원_라벨링_모델선정/결과_데이터_32/박상원/video_frames/안전비디오/..__비디오__video_128_drunk_driving",
  "frames_per_clip": 32,
  "clip_sec": 23.966666666666665,
  "clips": [
    {
      "index": 0,
      "start_sec": 0.0,
      "end_sec": 23.966666666666665,
      "topk": [
        {
          "index": 199,
          "label": "pushing cart\t199",
          "prob": 0.1754113733768463
        },
        {
          "index": 22,
          "label": "hurling (sport)\t22",
          "prob": 0.13226458430290222
        },
        {
          "index": 326,
          "label": "busking\t326",
          "prob": 0.11879463493824005
        },
        {
          "index": 309,
          "label": "playing guitar\t309",
          "prob": 0.10816916078329086
        },
        {
          "index": 322,
          "label": "waxing chest\t322",
          "prob": 0.09068664163351059
        }
      ],
      "top1_prob": 0.1754113733768463,
      "violence_hint": 0.0
    }
  ],
  "overall": {
    "num_clips": 1,
    "avg_top1_prob": 0.1754113733768463,
    "max_top1_prob": 0.1754113733768463,
    "avg_violence_hint": 0.0,
    "max_violence_hint": 0.0
  }
}