{
  "pexels-bohlemedia-1089930.jpg": 1,
  "pexels-elevate-1267323.jpg": 1,
  "pexels-elina-sazonova-1850595.jpg": 1,
  "pexels-elina-sazonova-1927313.jpg": 1,
  "pexels-energepic-com-27411-288476.jpg": 1,
  "pexels-enginakyurt-1672304.jpg": 1,
  "pexels-hygor-sakai-1214427-2311714.jpg": 1,
  "pexels-isabella-mendes-107313-1304475.jpg": 1,
  "pexels-isabella-mendes-107313-338713.jpg": 1,
  "pexels-isabella-mendes-107313-340996.jpg": 1,
  "pexels-med-yassin-ghaoui-1317271-2529468.jpg": 1,
  "pexels-pixabay-255483.jpg": 1,
  "pexels-terricks-noah-282960-936571.jpg": 1,
  "pexels-vijay-putra-13676-64738.jpg": 1,
  "pexels-cottonbro-4874515.jpg": 1,
  "pexels-cottonbro-5435555.jpg": 1,
  "pexels-cottonbro-5546478.jpg": 1,
  "pexels-holfotos-3115523.jpg": 1,
  "pexels-holfotos-3115525.jpg": 1,
  "pexels-karola-g-4195523.jpg": 1,
  "pexels-karola-g-7691779.jpg": 1,
  "pexels-karola-g-7691784.jpg": 1,
  "pexels-karola-g-7692054.jpg": 1,
  "pexels-pranidchakan-boonrom-101111-1350560.jpg": 1,
  "pexels-slaytinaaaa-3068932.jpg": 1,
  "pexels-connor-danylenko-534256-2574013.jpg": 1,
  "pexels-harrisonhaines-3536235.jpg": 1,
  "pexels-levi-damasceno-169031-571252.jpg": 1,
  "pexels-pixabay-264146.jpg": 1,
  "pexels-pixabay-415232.jpg": 1,
  "pexels-pixabay-417070.jpg": 1,
  "pexels-cottonbro-3923160.jpg": 1,
  "pexels-karola-g-4046999.jpg": 1,
  "pexels-karola-g-4047186.jpg": 1,
  "pexels-kevinbidwell-3602778.jpg": 1,
  "pexels-mart-production-7230226.jpg": 1,
  "pexels-mart-production-7231423.jpg": 1,
  "pexels-pietrozj-360622.jpg": 1,
  "pexels-pixabay-139398.jpg": 1,
  "pexels-pixabay-159211.jpg": 1,
  "pexels-pixabay-161688.jpg": 1,
  "pexels-pixabay-208512.jpg": 1,
  "pexels-pixabay-51929.jpg": 1,
  "pexels-shvetsa-3786119.jpg": 1,
  "pexels-shvetsa-3786157.jpg": 1,
  "pexels-suzyhazelwood-3652701.jpg": 1,
  "pexels-wmperspective-2919591.jpg": 1,
  "pexels-cottonbro-4980318.jpg": 1,
  "pexels-cottonbro-4980365.jpg": 1,
  "pexels-cottonbro-4980381.jpg": 1,
  "pexels-cottonbro-4980382.jpg": 1,
  "pexels-cottonbro-6475599.jpg": 1,
  "pexels-cottonbro-6559994.jpg": 1,
  "pexels-cottonbro-6568112.jpg": 1,
  "pexels-freestockpro-3819577.jpg": 1,
  "pexels-gantas-3647016.jpg": 1,
  "pexels-ketut-subiyanto-4746697.jpg": 1,
  "pexels-tim-samuel-5838841.jpg": 1,
  "pexels-yaroslav-shuraev-5085385.jpg": 1,
  "pexels-alex-qian-1180283-2474836.jpg": 1,
  "pexels-cottonbro-3779034.jpg": 1,
  "pexels-cottonbro-5446177.jpg": 1,
  "pexels-cottonbro-5932677.jpg": 1,
  "pexels-daniel-adesina-279287-2081068.jpg": 1,
  "pexels-denx-arman-3524452-5312244.jpg": 1,
  "pexels-denx-arman-3524452-5360500.jpg": 1,
  "pexels-elijahsad-3473525.jpg": 1,
  "pexels-iriser-798124.jpg": 1,
  "pexels-kampratt-3257717.jpg": 1,
  "pexels-maksgelatin-4663158.jpg": 1,
  "pexels-pixabay-70088.jpg": 1,
  "pexels-valeriiamiller-3361154.jpg": 1,
  "pexels-cottonbro-5435562.jpg": 1,
  "pexels-cottonbro-7266012.jpg": 1,
  "pexels-cottonbro-7299480.jpg": 1,
  "pexels-cottonbro-7299593.jpg": 1,
  "pexels-pavel-danilyuk-8638313.jpg": 1,
  "pexels-receptcelik-9076534.jpg": 1,
  "pexels-tima-miroshnichenko-5380640.jpg": 1,
  "pexels-aloismoubax-2348809.jpg": 1,
  "pexels-coco-championship-191448-598631.jpg": 1,
  "pexels-coco-championship-191448-598656.jpg": 1,
  "pexels-coco-championship-191448-598687.jpg": 1,
  "pexels-cottonbro-4100674.jpg": 1,
  "pexels-josh-hild-1270765-4508669.jpg": 1,
  "pexels-kampus-6765037.jpg": 1,
  "pexels-moklebust-5764701.jpg": 1,
  "pexels-musaortac-3586873.jpg": 1,
  "pexels-pixabay-70567.jpg": 1,
  "pexels-andiravsanjani-3678429.jpg": 1,
  "pexels-ferdinandstudio-34799846.jpg": 1,
  "pexels-goumbik-952366.jpg": 1,
  "pexels-mabel-lee-1391205-2739752.jpg": 1,
  "pexels-manuela-kohl-16633-103891.jpg": 1,
  "pexels-osmachko-213084.jpg": 1,
  "pexels-pixabay-163347.jpg": 1,
  "pexels-pixabay-163443.jpg": 1,
  "pexels-pixabay-163480.jpg": 1,
  "pexels-pixabay-78783.jpg": 1,
  "pexels-specna-arms-306304-886454.jpg": 1,
  "pexels-specna-arms-306304-889709.jpg": 1,
  "pexels-suju-1383766.jpg": 1
}