{
  "model": "jaranohaal/vit-base-violence-detection",
  "frames_dir": "/home/jovyan/kau-muhayu-multimodal-harmful-content-detect/임영재/팀원_라벨링/팀원_데이터/video_frames/NV_826",
  "num_frames_total": 137,
  "num_frames_used": 14,
  "per_frame": {
    "clip_000_frame_000.jpg": {
      "violence_prob": 0.2064988762140274
    },
    "clip_000_frame_010.jpg": {
      "violence_prob": 0.17935578525066376
    },
    "clip_000_frame_020.jpg": {
      "violence_prob": 0.2101605087518692
    },
    "clip_000_frame_030.jpg": {
      "violence_prob": 0.2247878611087799
    },
    "clip_000_frame_040.jpg": {
      "violence_prob": 0.22298021614551544
    },
    "clip_001_frame_000.jpg": {
      "violence_prob": 0.21427009999752045
    },
    "clip_001_frame_010.jpg": {
      "violence_prob": 0.2111937403678894
    },
    "clip_001_frame_020.jpg": {
      "violence_prob": 0.1690278947353363
    },
    "clip_001_frame_030.jpg": {
      "violence_prob": 0.15635612607002258
    },
    "clip_001_frame_040.jpg": {
      "violence_prob": 0.15630818903446198
    },
    "clip_002_frame_000.jpg": {
      "violence_prob": 0.1604313850402832
    },
    "clip_002_frame_010.jpg": {
      "violence_prob": 0.16555950045585632
    },
    "clip_002_frame_020.jpg": {
      "violence_prob": 0.16751383244991302
    },
    "clip_002_frame_030.jpg": {
      "violence_prob": 0.1813298761844635
    }
  },
  "overall": {
    "avg_violence_prob": 0.1875552779861859,
    "max_violence_prob": 0.2247878611087799,
    "p95_violence_prob": 0.223612891882658
  }
}